ochelper/__init__.py
ochelper/ochandler.py
ochelper/ochelper.py
ochelper/codeproc/CodeMatch.py
ochelper/codeproc/CodeWrite.py
ochelper/codeproc/ObjectiveClass.py
ochelper/codeproc/__init__.py
ochelper/fileproc/FileProc.py
ochelper/fileproc/__init__.py
ochelper-0.0.6.dist-info/LICENSE.txt
ochelper-0.0.6.dist-info/METADATA
ochelper-0.0.6.dist-info/WHEEL
ochelper-0.0.6.dist-info/entry_points.txt
ochelper-0.0.6.dist-info/top_level.txt
ochelper-0.0.6.dist-info/RECORD
