Metadata-Version: 2.1
Name: ochelper
Version: 0.0.6
Summary: ochelper for objective-c
Home-page: https://github.com
Author: weishqdev
Author-email: weishqdev@gmail.com
License: UNKNOWN
Keywords: objective-c code proc
Platform: UNKNOWN
Classifier: Development Status :: 3 - Alpha
Classifier: Intended Audience :: Developers
Classifier: Topic :: Software Development :: Build Tools
Classifier: License :: OSI Approved :: MIT License
Classifier: Programming Language :: Python :: 2
Classifier: Programming Language :: Python :: 2.7
